flake8_dunder_all/__init__.py
flake8_dunder_all/__main__.py
flake8_dunder_all/py.typed
flake8_dunder_all/utils.py
flake8_dunder_all-0.5.0.dist-info/LICENSE
flake8_dunder_all-0.5.0.dist-info/METADATA
flake8_dunder_all-0.5.0.dist-info/WHEEL
flake8_dunder_all-0.5.0.dist-info/entry_points.txt
flake8_dunder_all-0.5.0.dist-info/RECORD
