Metadata-Version: 2.2
Name: flake8-dunder-all
Version: 0.5.0
Summary: A Flake8 plugin and pre-commit hook which checks to ensure modules have defined '__all__'.
Author-email: Dominic Davis-Foster <dominic@davis-foster.co.uk>
License: MIT
Keywords: flake8
Home-page: https://github.com/python-formate/flake8-dunder-all
Project-URL: Issue Tracker, https://github.com/python-formate/flake8-dunder-all/issues
Project-URL: Source Code, https://github.com/python-formate/flake8-dunder-all
Project-URL: Documentation, https://flake8-dunder-all.readthedocs.io/en/latest
Platform: Windows
Platform: macOS
Platform: Linux
Classifier: Development Status :: 4 - Beta
Classifier: Framework :: Flake8
Classifier: Intended Audience :: Developers
Classifier: License :: OSI Approved :: MIT License
Classifier: Operating System :: OS Independent
Classifier: Programming Language :: Python
Classifier: Programming Language :: Python :: 3 :: Only
Classifier: Programming Language :: Python :: 3.7
Classifier: Programming Language :: Python :: 3.8
Classifier: Programming Language :: Python :: 3.9
Classifier: Programming Language :: Python :: 3.10
Classifier: Programming Language :: Python :: 3.11
Classifier: Programming Language :: Python :: 3.12
Classifier: Programming Language :: Python :: Implementation :: CPython
Classifier: Programming Language :: Python :: Implementation :: PyPy
Classifier: Topic :: Utilities
Classifier: Typing :: Typed
Requires-Python: >=3.7
Requires-Dist: astatine>=0.3.1
Requires-Dist: click>=7.1.2
Requires-Dist: consolekit>=0.8.1
Requires-Dist: domdf-python-tools>=2.6.0
Requires-Dist: flake8>=3.7
Requires-Dist: natsort>=8.0.2
